git_railway/__init__.py
git_railway/__main__.py
git_railway/adt.py
git_railway/model.py
git_railway/resources/__init__.py
git_railway/resources/git_railway.html
git_railway/resources/popup.js
git_railway/resources/style.css
git_railway/view/__init__.py
git_railway/view/html.py
git_railway/view/svg.py
git_railway-0.3.0.dist-info/entry_points.txt
git_railway-0.3.0.dist-info/LICENSE.md
git_railway-0.3.0.dist-info/WHEEL
git_railway-0.3.0.dist-info/METADATA
git_railway-0.3.0.dist-info/RECORD
