Metadata-Version: 2.1
Name: git-railway
Version: 0.3.0
Summary: Visualise local git branches as neat interactive HTML pages
Home-page: https://github.com/P403n1x87/git-railway
License: GPL-3.0-or-later
Keywords: tools,scm
Author: Gabriele N. Tornetta
Author-email: phoenix1987@gmail.com
Requires-Python: >=3.6,<4.0
Classifier: Development Status :: 4 - Beta
Classifier: Intended Audience :: Developers
Classifier: License :: OSI Approved :: GNU General Public License v3 or later (GPLv3+)
Classifier: Programming Language :: Python :: 3
Classifier: Programming Language :: Python :: 3.6
Classifier: Programming Language :: Python :: 3.7
Classifier: Programming Language :: Python :: 3.8
Classifier: Programming Language :: Python :: 3.9
Requires-Dist: GitPython (>=3.1.8,<4.0.0)
Requires-Dist: colour (>=0.1.5,<0.2.0)
Requires-Dist: dataclasses
Requires-Dist: importlib_resources (>=3.1.1,<4.0.0)
Requires-Dist: svgwrite (>=1.4,<2.0)
Project-URL: Repository, https://github.com/P403n1x87/git-railway
